integrimark/__init__.py
integrimark/encryption.py
integrimark/github.py
integrimark/helpers.py
integrimark/integrimark.pack.html
integrimark/integrimark.solutions-email.jinja2.html
integrimark/mailing.py
integrimark/utils.py
integrimark-0.1.3.dist-info/LICENSE.md
integrimark-0.1.3.dist-info/METADATA
integrimark-0.1.3.dist-info/WHEEL
integrimark-0.1.3.dist-info/entry_points.txt
integrimark-0.1.3.dist-info/RECORD
