Metadata-Version: 2.1
Name: integrimark
Version: 0.1.3
Summary: IntegriMark is a system that protects digital PDF documents by watermarking them with user-specific details, ensuring traceability and discouraging unauthorized sharing.
License: LPGLv3
Author: Jérémie Lumbroso
Author-email: lumbroso@seas.upenn.edu
Requires-Python: >=3.11,<4.0
Classifier: License :: Other/Proprietary License
Classifier: Programming Language :: Python :: 3
Classifier: Programming Language :: Python :: 3.11
Requires-Dist: click (>=8.1.7,<9.0.0)
Requires-Dist: click-help-colors (>=0.9.4,<0.10.0)
Requires-Dist: gspread (>=5.12.0,<6.0.0)
Requires-Dist: jinja2 (>=3.1.2,<4.0.0)
Requires-Dist: loguru (>=0.7.2,<0.8.0)
Requires-Dist: markdownify (>=0.11.6,<0.12.0)
Requires-Dist: pycryptodome (>=3.19.0,<4.0.0)
Requires-Dist: python-dotenv (>=1.0.0,<2.0.0)
Requires-Dist: requests (>=2.31.0,<3.0.0)
Requires-Dist: sendgrid (>=6.10.0,<7.0.0)
Requires-Dist: tqdm (>=4.66.1,<5.0.0)
Requires-Dist: xkcdpass (>=1.19.4,<2.0.0)
